tcrgeometry-0.1.1.dist-info/licenses/LICENSE
trangle/__init__.py
trangle/anarci_numbering.py
trangle/calc_geometry.py
trangle/calc_geometry_MD.py
trangle/change_geometry.py
trangle/get_anchor_coords.py
trangle/number_old.py
trangle/data/__init__.py
trangle/data/consensus_output/chain_A/average_structure.pdb
trangle/data/consensus_output/chain_A/average_structure_pca_vis.png
trangle/data/consensus_output/chain_A/average_structure_pca_vis.pse
trangle/data/consensus_output/chain_A/average_structure_pca_vis.py
trangle/data/consensus_output/chain_A/average_structure_with_pca.pdb
trangle/data/consensus_output/chain_A/consensus_alignment_residues.txt
trangle/data/consensus_output/chain_A/per_residue_alignment_scores.csv
trangle/data/consensus_output/chain_A/per_residue_rmsd_plot.png
trangle/data/consensus_output/chain_B/average_structure.pdb
trangle/data/consensus_output/chain_B/average_structure_pca_vis.png
trangle/data/consensus_output/chain_B/average_structure_pca_vis.pse
trangle/data/consensus_output/chain_B/average_structure_pca_vis.py
trangle/data/consensus_output/chain_B/average_structure_with_pca.pdb
trangle/data/consensus_output/chain_B/consensus_alignment_residues.txt
trangle/data/consensus_output/chain_B/per_residue_alignment_scores.csv
trangle/data/consensus_output/chain_B/per_residue_rmsd_plot.png
tcrgeometry-0.1.1.dist-info/METADATA
tcrgeometry-0.1.1.dist-info/WHEEL
tcrgeometry-0.1.1.dist-info/entry_points.txt
tcrgeometry-0.1.1.dist-info/top_level.txt
tcrgeometry-0.1.1.dist-info/RECORD
