Metadata-Version: 2.4
Name: tcrgeometry
Version: 0.1.1
Summary: TCR geometry calculation and visualization tools
Author-email: Lilian Denzler <lilian.denzler@yale.edu>
License: MIT License
Project-URL: Homepage, https://github.com/LilianDenzler/TCRangle
Project-URL: Issues, https://github.com/LilianDenzler/TCRangle/issues
Requires-Python: >=3.9
License-File: LICENSE
Requires-Dist: numpy>=1.22
Requires-Dist: pandas>=1.5
Requires-Dist: biopython>=1.80
Requires-Dist: biotite>=0.40
Requires-Dist: MDAnalysis>=2.4
Requires-Dist: tqdm>=4.65
Provides-Extra: vis
Requires-Dist: pymol-open-source>=2.5; extra == "vis"
Dynamic: license-file
